{"width":512,"SubTexture":[{"frameY":-94,"y":188,"frameWidth":128,"frameX":-38,"frameHeight":128,"width":53,"height":18,"name":"start_03","x":1},{"frameY":-107,"y":76,"frameWidth":128,"frameX":-56,"frameHeight":128,"width":16,"height":5,"name":"start_01","x":121},{"frameY":-19,"y":161,"frameWidth":128,"frameX":-47,"frameHeight":128,"width":34,"height":93,"name":"start_04","x":282},{"frameY":-97,"y":208,"frameWidth":128,"frameX":-44,"frameHeight":128,"width":40,"height":15,"name":"start_02","x":1},{"frameY":-30,"y":95,"frameWidth":128,"frameX":-37,"frameHeight":128,"width":58,"height":82,"name":"Infinite_07","x":59},{"frameY":-21,"y":95,"frameWidth":128,"frameX":-38,"frameHeight":128,"width":56,"height":91,"name":"Infinite_04","x":1},{"frameY":-27,"y":1,"frameWidth":128,"frameX":-40,"frameHeight":128,"width":51,"height":85,"name":"Infinite_02","x":174},{"frameY":-30,"y":161,"frameWidth":128,"frameX":-43,"frameHeight":128,"width":41,"height":82,"name":"Infinite_08","x":239},{"frameY":-24,"y":85,"frameWidth":128,"frameX":-39,"frameHeight":128,"width":53,"height":88,"name":"Infinite_03","x":119},{"frameY":-20,"y":1,"frameWidth":128,"frameX":-37,"frameHeight":128,"width":58,"height":92,"name":"Infinite_05","x":1},{"frameY":-30,"y":1,"frameWidth":128,"frameX":-37,"frameHeight":128,"width":58,"height":82,"name":"Infinite_06","x":61},{"frameY":-28,"y":1,"frameWidth":128,"frameX":-41,"frameHeight":128,"width":49,"height":84,"name":"Infinite_01","x":227},{"frameY":-42,"y":1,"frameWidth":128,"frameX":-38,"frameHeight":128,"width":56,"height":70,"name":"End_08","x":278},{"frameY":-39,"y":88,"frameWidth":128,"frameX":-39,"frameHeight":128,"width":57,"height":73,"name":"End_06","x":174},{"frameY":-40,"y":87,"frameWidth":128,"frameX":-39,"frameHeight":128,"width":57,"height":72,"name":"End_05","x":233},{"frameY":-32,"y":175,"frameWidth":128,"frameX":-39,"frameHeight":128,"width":57,"height":80,"name":"End_04","x":180},{"frameY":-38,"y":179,"frameWidth":128,"frameX":-38,"frameHeight":128,"width":58,"height":74,"name":"End_07","x":59},{"frameY":-39,"y":1,"frameWidth":128,"frameX":-39,"frameHeight":128,"width":50,"height":73,"name":"End_02","x":121},{"frameY":-34,"y":161,"frameWidth":128,"frameX":-44,"frameHeight":128,"width":40,"height":78,"name":"End_01","x":318},{"frameY":-32,"y":175,"frameWidth":128,"frameX":-39,"frameHeight":128,"width":57,"height":80,"name":"End_03","x":121}],"height":256,"name":"WaterBlast","imagePath":"WaterBlast_tex.png"}